crop_image/__init__.py
crop_image/cropimg.py
crop_image/update_image.py
crop_image/update_image_adb.py
crop_image/update_image_desktop.py
cropimg-0.2.0.dist-info/LICENSE
cropimg-0.2.0.dist-info/METADATA
cropimg-0.2.0.dist-info/WHEEL
cropimg-0.2.0.dist-info/entry_points.txt
cropimg-0.2.0.dist-info/top_level.txt
cropimg-0.2.0.dist-info/RECORD
